update_db/__init__.py
update_db/update_db.py
update_db-0.0.1.dist-info/LICENSE
update_db-0.0.1.dist-info/METADATA
update_db-0.0.1.dist-info/WHEEL
update_db-0.0.1.dist-info/top_level.txt
update_db-0.0.1.dist-info/RECORD
