Metadata-Version: 2.1
Name: update-db
Version: 0.0.1
Summary: For update db
Home-page: UNKNOWN
Author: Minh Dang
Author-email: minhdang@kms-technology.com
License: UNKNOWN
Platform: UNKNOWN
Classifier: Programming Language :: Python :: 3
Classifier: License :: OSI Approved :: MIT License
Classifier: Operating System :: OS Independent
Requires-Python: >=3.7
License-File: LICENSE
